compas_mobile_robot_reloc/__init__.py
compas_mobile_robot_reloc/__main__.py
compas_mobile_robot_reloc/_version.py
compas_mobile_robot_reloc/arbitrary_pts_localization.py
compas_mobile_robot_reloc/measurement_point.py
compas_mobile_robot_reloc/py.typed
compas_mobile_robot_reloc/three_pts_localization.py
compas_mobile_robot_reloc/utils.py
compas_mobile_robot_reloc/xforms.py
compas_mobile_robot_reloc-1.0.7.dist-info/LICENSE
compas_mobile_robot_reloc-1.0.7.dist-info/METADATA
compas_mobile_robot_reloc-1.0.7.dist-info/WHEEL
compas_mobile_robot_reloc-1.0.7.dist-info/top_level.txt
compas_mobile_robot_reloc-1.0.7.dist-info/RECORD
