Metadata-Version: 2.1
Name: compas-mobile-robot-reloc
Version: 1.0.7
Summary: Robot localization using external measuring device (total station).
Home-page: https://gramaziokohler.github.io/compas_mobile_robot_reloc
Author: Gramazio Kohler Research
Maintainer: Anton Tetov Johansson
Maintainer-email: anton@tetov.se
License: MIT license
Project-URL: Repository, https://github.com/gramaziokohler/compas_mobile_robot_reloc
Project-URL: Issues, https://github.com/gramaziokohler/compas_mobile_robot_reloc/issues
Project-URL: Documentation, https://gramaziokohler.github.io/compas_mobile_robot_reloc
Keywords: architecture,engineering,fabrication,construction
Platform: UNKNOWN
Classifier: Development Status :: 4 - Beta
Classifier: Intended Audience :: Developers
Classifier: Topic :: Scientific/Engineering
Classifier: License :: OSI Approved :: MIT License
Classifier: Operating System :: Unix
Classifier: Operating System :: POSIX
Classifier: Operating System :: Microsoft :: Windows
Classifier: Programming Language :: Python
Classifier: Programming Language :: Python :: 3
Classifier: Programming Language :: Python :: 3.7
Classifier: Programming Language :: Python :: 3.8
Classifier: Programming Language :: Python :: Implementation :: CPython
Classifier: Programming Language :: Python :: Implementation :: IronPython
Requires-Python: >=3.7
License-File: LICENSE
Requires-Dist: compas (<1.8,>=0.17.2)
Provides-Extra: dev
Requires-Dist: black (>=20.8b1) ; extra == 'dev'
Requires-Dist: doc8 ; extra == 'dev'
Requires-Dist: flake8 ; extra == 'dev'
Requires-Dist: invoke (<1.7,>=1.5) ; extra == 'dev'
Requires-Dist: isort (>=5.6.4) ; extra == 'dev'
Requires-Dist: m2r2 (~=0.2) ; extra == 'dev'
Requires-Dist: mypy (>=0.790) ; extra == 'dev'
Requires-Dist: pre-commit ; extra == 'dev'
Requires-Dist: pydocstyle (<7.0,>=5.1) ; extra == 'dev'
Requires-Dist: pytest (~=6.1) ; extra == 'dev'
Requires-Dist: pytest-cov ; extra == 'dev'
Requires-Dist: sphinx (>=3.3) ; extra == 'dev'
Requires-Dist: sphinx-compas-theme (~=0.11) ; extra == 'dev'
Requires-Dist: setuptools-scm[toml] (<7.0,>=4.1) ; extra == 'dev'
Requires-Dist: importlib-metadata ; (python_version < "3.8") and extra == 'dev'
